fontname.py
fontname-1.0.0.dist-info/LICENSE.txt
fontname-1.0.0.dist-info/WHEEL
fontname-1.0.0.dist-info/METADATA
fontname-1.0.0.dist-info/RECORD
