Metadata-Version: 2.1
Name: fontname
Version: 1.0.0
Summary: Read and decode quirk encoded name records from OpenType fonts.
Author-email: Asvel <fe.asvel@gmail.com>
Requires-Python: ~=3.7
Classifier: Development Status :: 5 - Production/Stable
Classifier: Intended Audience :: Developers
Classifier: Programming Language :: Python :: 3
Classifier: License :: OSI Approved :: MIT License
Classifier: Operating System :: OS Independent
Classifier: Topic :: Software Development :: Libraries :: Python Modules
Classifier: Topic :: Text Processing :: Fonts
Requires-Dist: fonttools >=4
Project-URL: Home, https://github.com/Asvel/fontname
